{"meta":{"type":"db","canSave":false,"canEdit":false,"canAdmin":false,"canStar":true,"canDelete":false,"slug":"slit","url":"/d/cdifddd2mn0g0e/slit","expires":"0001-01-01T00:00:00Z","created":"2025-02-05T16:59:02+09:00","updated":"2025-02-05T16:59:16+09:00","updatedBy":"admin","createdBy":"admin","version":2,"hasAcl":false,"isFolder":false,"folderId":1,"folderUid":"f8cdd9a2-bcef-4f56-8dae-8325f4cd491d","folderTitle":"E73","folderUrl":"/dashboards/f/f8cdd9a2-bcef-4f56-8dae-8325f4cd491d/e73","provisioned":false,"provisionedExternalId":"","annotationsPermissions":{"dashboard":{"canAdd":true,"canEdit":true,"canDelete":true},"organization":{"canAdd":false,"canEdit":false,"canDelete":false}}},"dashboard":{"annotations":{"list":[{"builtIn":1,"datasource":{"type":"grafana","uid":"-- Grafana --"},"enable":true,"hide":true,"iconColor":"rgba(0, 211, 255, 1)","name":"Annotations \u0026 Alerts","type":"dashboard"}]},"editable":true,"fiscalYearStartMonth":0,"graphTooltip":0,"id":14,"links":[],"liveNow":false,"panels":[{"datasource":{"type":"grafana-postgresql-datasource","uid":"ae5e5b0e-80a3-4f97-ba03-4b42c63ec9cb"},"description":"","fieldConfig":{"defaults":{"color":{"mode":"thresholds"},"mappings":[],"thresholds":{"mode":"absolute","steps":[{"color":"green","value":null}]},"unit":"lengthmm"},"overrides":[]},"gridPos":{"h":11,"w":24,"x":0,"y":0},"id":2,"options":{"colorMode":"value","graphMode":"area","justifyMode":"auto","orientation":"auto","percentChangeColorMode":"standard","reduceOptions":{"calcs":["lastNotNull"],"fields":"","values":false},"showPercentChange":false,"textMode":"auto","wideLayout":true},"pluginVersion":"10.2.6","targets":[{"datasource":{"type":"grafana-postgresql-datasource","uid":"bdgem37liwjcwe"},"editorMode":"code","format":"table","rawQuery":true,"rawSql":"SELECT  ifh_minus_cor, ifh_plus_cor, ifv_minus_cor, ifv_plus_cor,\n mom_minus_cor, mom_plus_cor, mass1_minus_cor, mass1_plus_cor \nFROM slit\nORDER BY timestamp DESC\nLIMIT 1","refId":"A","sql":{"columns":[{"parameters":[],"type":"function"}],"groupBy":[{"property":{"type":"string"},"type":"groupBy"}],"limit":50}}],"type":"stat"},{"datasource":{"type":"grafana-postgresql-datasource","uid":"ae5e5b0e-80a3-4f97-ba03-4b42c63ec9cb"},"description":"","fieldConfig":{"defaults":{"color":{"mode":"thresholds"},"mappings":[],"thresholds":{"mode":"absolute","steps":[{"color":"green","value":null}]},"unit":"volt"},"overrides":[]},"gridPos":{"h":10,"w":24,"x":0,"y":11},"id":1,"options":{"colorMode":"value","graphMode":"area","justifyMode":"auto","orientation":"auto","percentChangeColorMode":"standard","reduceOptions":{"calcs":["lastNotNull"],"fields":"","values":false},"showPercentChange":false,"textMode":"auto","wideLayout":true},"pluginVersion":"10.2.6","targets":[{"datasource":{"type":"grafana-postgresql-datasource","uid":"bdgem37liwjcwe"},"editorMode":"code","format":"table","rawQuery":true,"rawSql":"SELECT  ifh_minus_raw, ifh_plus_raw, ifv_minus_raw, ifv_plus_raw,\n mom_minus_raw, mom_plus_raw, mass1_minus_raw, mass1_plus_raw \nFROM slit\nORDER BY timestamp DESC\nLIMIT 1","refId":"A","sql":{"columns":[{"parameters":[],"type":"function"}],"groupBy":[{"property":{"type":"string"},"type":"groupBy"}],"limit":50}}],"type":"stat"}],"refresh":"","schemaVersion":39,"tags":[],"templating":{"list":[]},"time":{"from":"now-6h","to":"now"},"timepicker":{},"timezone":"browser","title":"Slit","uid":"cdifddd2mn0g0e","version":2,"weekStart":""}}
